DBSQLite/__init__.py
DBSQLite/sqlite.py
DBSQLite-1.0.1.dist-info/LICENSE
DBSQLite-1.0.1.dist-info/METADATA
DBSQLite-1.0.1.dist-info/WHEEL
DBSQLite-1.0.1.dist-info/top_level.txt
DBSQLite-1.0.1.dist-info/RECORD
