Metadata-Version: 2.1
Name: DBSQLite
Version: 1.0.1
Summary: A lightweight SQLite helper library.
Home-page: https://github.com/alisx/DBSQLite
Author: alec
Author-email: aalisx@gmail.com
License: MIT
Classifier: Programming Language :: Python :: 3
Classifier: License :: OSI Approved :: MIT License
Classifier: Operating System :: OS Independent
Requires-Python: >=3.6
License-File: LICENSE
